sqlalchemy_orderingitem/__init__.py
sqlalchemy_orderingitem-0.0.5.dist-info/LICENSE
sqlalchemy_orderingitem-0.0.5.dist-info/METADATA
sqlalchemy_orderingitem-0.0.5.dist-info/WHEEL
sqlalchemy_orderingitem-0.0.5.dist-info/top_level.txt
sqlalchemy_orderingitem-0.0.5.dist-info/RECORD
