Metadata-Version: 2.1
Name: sqlalchemy-orderingitem
Version: 0.0.5
Summary: SQLAlchemy-OrderingItem provides an OrderingItem base for children of orderinglist relationships.
Home-page: https://dsbowen.github.io/sqlalchemy-orderingitem/
Author: Dillon Bowen
Author-email: dsbowen@wharton.upenn.edu
License: UNKNOWN
Platform: UNKNOWN
Classifier: Programming Language :: Python :: 3
Classifier: License :: OSI Approved :: MIT License
Classifier: Operating System :: OS Independent
Requires-Python: >=3.6
Requires-Dist: sqlalchemy (>=1.3.12)
